odoo8_addon_mrp_production_real_cost-8.0.1.0.2.99.dev25-py2.7-nspkg.pth
odoo8_addon_mrp_production_real_cost-8.0.1.0.2.99.dev25.dist-info/DESCRIPTION.rst
odoo8_addon_mrp_production_real_cost-8.0.1.0.2.99.dev25.dist-info/METADATA
odoo8_addon_mrp_production_real_cost-8.0.1.0.2.99.dev25.dist-info/RECORD
odoo8_addon_mrp_production_real_cost-8.0.1.0.2.99.dev25.dist-info/WHEEL
odoo8_addon_mrp_production_real_cost-8.0.1.0.2.99.dev25.dist-info/metadata.json
odoo8_addon_mrp_production_real_cost-8.0.1.0.2.99.dev25.dist-info/namespace_packages.txt
odoo8_addon_mrp_production_real_cost-8.0.1.0.2.99.dev25.dist-info/top_level.txt
odoo_addons/mrp_production_real_cost/README.rst
odoo_addons/mrp_production_real_cost/__init__.py
odoo_addons/mrp_production_real_cost/__openerp__.py
odoo_addons/mrp_production_real_cost/data/analytic_journal_data.xml
odoo_addons/mrp_production_real_cost/demo/mrp_production_demo.xml
odoo_addons/mrp_production_real_cost/i18n/ca.po
odoo_addons/mrp_production_real_cost/i18n/cs.po
odoo_addons/mrp_production_real_cost/i18n/de.po
odoo_addons/mrp_production_real_cost/i18n/en_US.po
odoo_addons/mrp_production_real_cost/i18n/es.po
odoo_addons/mrp_production_real_cost/i18n/es_AR.po
odoo_addons/mrp_production_real_cost/i18n/es_MX.po
odoo_addons/mrp_production_real_cost/i18n/fi.po
odoo_addons/mrp_production_real_cost/i18n/fr.po
odoo_addons/mrp_production_real_cost/i18n/gl.po
odoo_addons/mrp_production_real_cost/i18n/hr.po
odoo_addons/mrp_production_real_cost/i18n/it.po
odoo_addons/mrp_production_real_cost/i18n/mrp_production_real_cost.pot
odoo_addons/mrp_production_real_cost/i18n/pt.po
odoo_addons/mrp_production_real_cost/i18n/pt_BR.po
odoo_addons/mrp_production_real_cost/i18n/ro.po
odoo_addons/mrp_production_real_cost/i18n/sl.po
odoo_addons/mrp_production_real_cost/i18n/tr.po
odoo_addons/mrp_production_real_cost/i18n/tr_TR.po
odoo_addons/mrp_production_real_cost/i18n/vi_VN.po
odoo_addons/mrp_production_real_cost/i18n/zh_CN.po
odoo_addons/mrp_production_real_cost/models/__init__.py
odoo_addons/mrp_production_real_cost/models/mrp_bom.py
odoo_addons/mrp_production_real_cost/models/mrp_production.py
odoo_addons/mrp_production_real_cost/models/mrp_production_workcenter_line.py
odoo_addons/mrp_production_real_cost/models/stock_move.py
odoo_addons/mrp_production_real_cost/static/description/icon.png
odoo_addons/mrp_production_real_cost/static/description/icon.svg
odoo_addons/mrp_production_real_cost/static/description/mrp_real_cost.png
