Metadata-Version: 2.0
Name: odoo8-addon-mrp-production-real-cost
Version: 8.0.1.0.2.99.dev25
Summary: Real costs in manufacturing orders
Home-page: UNKNOWN
Author: OdooMRP team, AvanzOSC, Serv. Tecnol. Avanzados - Pedro M. Baeza, Antiun Ingeniería S.L., Odoo Community Association (OCA)
Author-email: support@odoo-community.org
License: AGPL-3
Platform: UNKNOWN
Classifier: Programming Language :: Python
Classifier: Framework :: Odoo
Classifier: License :: OSI Approved :: GNU Affero General Public License v3
Requires-Python: ~=2.7
Requires-Dist: odoo (<9.0a,>=8.0a)
Requires-Dist: odoo8-addon-mrp-operations-extension
Requires-Dist: odoo8-addon-mrp-operations-time-control
Requires-Dist: odoo8-addon-mrp-project
